pyqqmusicdes.cpython-313-aarch64-linux-gnu.so
pyqqmusicdes/__init__.pyi
pyqqmusicdes-0.1.1.dist-info/METADATA
pyqqmusicdes-0.1.1.dist-info/WHEEL
pyqqmusicdes-0.1.1.dist-info/top_level.txt
pyqqmusicdes-0.1.1.dist-info/RECORD
