Metadata-Version: 2.4
Name: pyqqmusicdes
Version: 0.1.1
Summary: A Python wrapper for the QQ Music DES encryption algorithm
Author-email: Maxr1998 <max@maxr1998.de>
License-Expression: MIT
Requires-Python: >=3.10
